horus/__init__.py
horus/compiler/__init__.py
horus/compiler/allowed_syscalls.py
horus/compiler/code_elements.py
horus/compiler/contract_definition.py
horus/compiler/horus.ebnf
horus/compiler/horus_compile.py
horus/compiler/parser.py
horus/compiler/parser_transformer.py
horus/compiler/preprocessor.py
horus/compiler/type_checker.py
horus/compiler/var_names.py
horus/compiler/z3_transformer.py
horus/horus_error.py
horus/scripts/horus-compile
horus/utils.py
horus_compile-0.0.6.13.dist-info/LICENSE
horus_compile-0.0.6.13.dist-info/METADATA
horus_compile-0.0.6.13.dist-info/WHEEL
horus_compile-0.0.6.13.dist-info/entry_points.txt
horus_compile-0.0.6.13.dist-info/RECORD
