Metadata-Version: 2.1
Name: horus-compile
Version: 0.0.6.13
Summary: Use formally verified annotations in your Cairo code
License: APACHE LICENSE, VERSION 2.0
Author: Nethermind
Author-email: hello@nethermind.io
Maintainer: Ganesh Tiwari
Maintainer-email: ganesh@nethermind.io
Requires-Python: >=3.7,<3.10
Classifier: License :: OSI Approved :: Apache Software License
Classifier: License :: Other/Proprietary License
Classifier: Programming Language :: Python :: 3
Classifier: Programming Language :: Python :: 3.7
Classifier: Programming Language :: Python :: 3.8
Classifier: Programming Language :: Python :: 3.9
Classifier: Programming Language :: Python :: 3.7
Requires-Dist: cairo-lang (==0.10.1)
Requires-Dist: eth-utils (>=1.2.0,<2.0.0)
Requires-Dist: lark (>=1.1.4,<2.0.0)
Requires-Dist: marshmallow (>=3.15.0,<4.0.0)
Requires-Dist: marshmallow-dataclass (>=7.1.0,<8.5.4)
Requires-Dist: z3-solver (>=4.8.15,<5.0.0)
